metrological_quantity/__init__.py
metrological_quantity/quantity.py
metrological_quantity-1.0.1.dist-info/METADATA
metrological_quantity-1.0.1.dist-info/WHEEL
metrological_quantity-1.0.1.dist-info/licenses/LICENSE
metrological_quantity-1.0.1.dist-info/RECORD
