Metadata-Version: 2.4
Name: metrological-quantity
Version: 1.0.1
Summary: Simple arithmetic operations with quantities including units and uncertainties
Project-URL: Repository, https://github.com/xandratxan/metrological-quantity
Project-URL: Documentation, https://github.com/xandratxan/metrological-quantity/blob/main/README.md
Project-URL: Issues, https://github.com/xandratxan/metrological-quantity/issues
Author-email: Xandra Campo <xkmpera@gmail.com>
License:                     GNU GENERAL PUBLIC LICENSE
License-File: LICENSE
Keywords: arithmetics,metrology,uncertainty,units
Classifier: Development Status :: 5 - Production/Stable
Classifier: Intended Audience :: Science/Research
Classifier: Programming Language :: Python
Classifier: Programming Language :: Python :: 3
Classifier: Programming Language :: Python :: 3.6
Classifier: Topic :: Scientific/Engineering :: Physics
Requires-Python: >=3.6
